meta_memcache/__init__.py
meta_memcache/cache_client.py
meta_memcache/configuration.py
meta_memcache/errors.py
meta_memcache/protocol.py
meta_memcache/py.typed
meta_memcache/serializer.py
meta_memcache/settings.py
meta_memcache/base/__init__.py
meta_memcache/base/base_cache_client.py
meta_memcache/base/base_serializer.py
meta_memcache/commands/__init__.py
meta_memcache/commands/high_level_commands.py
meta_memcache/commands/meta_commands.py
meta_memcache/compression/__init__.py
meta_memcache/compression/zstd_manager.py
meta_memcache/connection/__init__.py
meta_memcache/connection/memcache_socket.py
meta_memcache/connection/pool.py
meta_memcache/connection/providers.py
meta_memcache/events/__init__.py
meta_memcache/events/write_failure_event.py
meta_memcache/executors/__init__.py
meta_memcache/executors/default.py
meta_memcache/extras/__init__.py
meta_memcache/extras/client_wrapper.py
meta_memcache/extras/migrating_cache_client.py
meta_memcache/extras/probabilistic_hot_cache.py
meta_memcache/interfaces/__init__.py
meta_memcache/interfaces/cache_api.py
meta_memcache/interfaces/commands.py
meta_memcache/interfaces/executor.py
meta_memcache/interfaces/high_level_commands.py
meta_memcache/interfaces/meta_commands.py
meta_memcache/interfaces/router.py
meta_memcache/metrics/__init__.py
meta_memcache/metrics/base.py
meta_memcache/metrics/prometheus.py
meta_memcache/routers/__init__.py
meta_memcache/routers/default.py
meta_memcache/routers/ephemeral.py
meta_memcache/routers/gutter.py
meta_memcache/routers/helpers.py
meta_memcache-2.0.5.dist-info/licenses/LICENSE
meta_memcache-2.0.5.dist-info/METADATA
meta_memcache-2.0.5.dist-info/WHEEL
meta_memcache-2.0.5.dist-info/top_level.txt
meta_memcache-2.0.5.dist-info/RECORD
