Metadata-Version: 2.4
Name: meta-memcache
Version: 2.0.5
Summary: Modern, pure python, memcache client with support for new meta commands.
Author-email: Guillermo Perez <bisho@revenuecat.com>
License: MIT License
Project-URL: homepage, https://github.com/RevenueCat/meta-memcache-py
Requires-Python: >=3.10
License-File: LICENSE
Requires-Dist: uhashring<3,>=2.3
Requires-Dist: marisa-trie<1.3,>=1.2.1
Requires-Dist: zstandard<0.26,>=0.25.0
Requires-Dist: meta-memcache-socket<0.2,>=0.1.3
Provides-Extra: metrics
Requires-Dist: prometheus-client>=0.17.1; extra == "metrics"
Dynamic: license-file
